tutorial_text2pdf_style/__init__.py
tutorial_text2pdf_style/__main__.py
tutorial_text2pdf_style/sample_output.png
tutorial_text2pdf_style-0.1.2.dist-info/METADATA
tutorial_text2pdf_style-0.1.2.dist-info/WHEEL
tutorial_text2pdf_style-0.1.2.dist-info/entry_points.txt
tutorial_text2pdf_style-0.1.2.dist-info/top_level.txt
tutorial_text2pdf_style-0.1.2.dist-info/RECORD
