Metadata-Version: 2.1
Name: tutorial-text2pdf-style
Version: 0.1.2
Summary: Convert cleanly formatted .txt documentation into color-styled PDF files.
Home-page: https://github.com/adhikaripb/coding-scripting-tutorial-pdf-generator
Author: Prakash Babu Adhikari
Author-email: your_email@example.com
Classifier: Programming Language :: Python :: 3
Classifier: License :: OSI Approved :: MIT License
Classifier: Operating System :: OS Independent
Requires-Python: >=3.7
Requires-Dist: fpdf
